README.txt
setup.cfg
setup.py
collective/__init__.py
collective.ordereddict.egg-info/PKG-INFO
collective.ordereddict.egg-info/SOURCES.txt
collective.ordereddict.egg-info/dependency_links.txt
collective.ordereddict.egg-info/entry_points.txt
collective.ordereddict.egg-info/namespace_packages.txt
collective.ordereddict.egg-info/not-zip-safe
collective.ordereddict.egg-info/paster_plugins.txt
collective.ordereddict.egg-info/requires.txt
collective.ordereddict.egg-info/top_level.txt
collective/ordereddict/__init__.py
collective/ordereddict/configure.zcml
collective/ordereddict/ordereddict.py
collective/ordereddict/tests.py
docs/HISTORY.txt
docs/INSTALL.txt
docs/LICENSE.GPL
docs/LICENSE.txt