Metadata-Version: 1.0
Name: collective.ordereddict
Version: 0.1
Summary: Ordered Dictionary for Python 2.4 or later
Home-page: http://svn.plone.org/svn/collective/collective.ordereddict
Author: Roel Bruggink
Author-email: roel@fourdigits.nl
License: GPL
Keywords: ordereddict ordered dict
Platform: UNKNOWN
Classifier: Framework :: Plone
Classifier: Programming Language :: Python
Classifier: Topic :: Software Development :: Libraries :: Python Modules
